riscv_pipe_implt/riscv_pipe_implt.srcs/sources_1/new/pc_adder.v
`timescale 1ns / 1ps
//////////////////////////////////////////////////////////////////////////////////
// Company: 
// Engineer: 
// 
// Create Date: 06/24/2025 01:45:39 PM
// Design Name: 
// Module Name: pc_adder
// Project Name: 
// Target Devices: 
// Tool Versions: 
// Description: 
// 
// Dependencies: 
// 
// Revision:
// Revision 0.01 - File Created
// Additional Comments:
// 
//////////////////////////////////////////////////////////////////////////////////


module pc_adder(
  input  [31 : 0] a,
  input  [31 : 0] b,
  
  output [31 : 0] c
);

  assign c= a +b;

endmodule

riscv_pipe_implt/riscv_pipe_implt.srcs/sim_1/new/tb_pc_adder.sv
`timescale 1ns / 1ps

module tb_pc_adder();

    // Test parameters
    parameter NUM_TESTS = 100;
    parameter CLK_PERIOD = 10;  // 100 MHz clock
    
    // DUT signals
    logic [31:0] a;
    logic [31:0] b;
    logic [31:0] c;
    
    // Testbench signals
    logic [31:0] expected_c;
    int error_count;
    logic clk;
    
    // Instantiate DUT
    pc_adder dut (
        .a(a),
        .b(b),
        .c(c)
    );
    
    // Clock generation
    initial begin
        clk = 1'b0;
        forever #(CLK_PERIOD/2) clk = ~clk;
    end
    
    // Main test sequence
    initial begin
        // Initialize
        error_count = 0;
        a = 32'h0;
        b = 32'h0;
        
        $display("\nStarting PC Adder Testbench\n");
        $timeformat(-9, 2, " ns", 10);
        
        // Test Case 1: Basic additions
        $display("[TEST 1] Basic additions");
        test_addition(32'h00000000, 32'h00000000, 32'h00000000, "0 + 0");
        test_addition(32'h00000001, 32'h00000001, 32'h00000002, "1 + 1");
        test_addition(32'h0000000A, 32'h00000005, 32'h0000000F, "10 + 5");
        test_addition(32'h0000FFFF, 32'h00000001, 32'h00010000, "65535 + 1");
        
        // Test Case 2: Boundary values
        $display("\n[TEST 2] Boundary values");
        test_addition(32'h7FFFFFFF, 32'h00000001, 32'h80000000, "Max positive + 1");
        test_addition(32'h80000000, 32'hFFFFFFFF, 32'h7FFFFFFF, "Min negative + -1");
        test_addition(32'hFFFFFFFF, 32'h00000001, 32'h00000000, "Max unsigned + 1");
        test_addition(32'hFFFFFFFF, 32'hFFFFFFFF, 32'hFFFFFFFE, "Max unsigned + Max unsigned");
        
        // Test Case 3: Signed number additions
        $display("\n[TEST 3] Signed number additions");
        test_addition(32'hFFFFFFFE, 32'h00000002, 32'h00000000, "-2 + 2");
        test_addition(32'hFFFFFFF0, 32'h00000020, 32'h00000010, "-16 + 32");
        test_addition(32'h80000000, 32'h7FFFFFFF, 32'hFFFFFFFF, "Min signed + Max signed");
        test_addition(32'hC0000000, 32'hC0000000, 32'h80000000, "-1073741824 + -1073741824");
        
        // Test Case 4: Random additions
        $display("\n[TEST 4] Random additions (%0d tests)", NUM_TESTS);
        for (int i = 0; i < NUM_TESTS; i++) begin
            logic [31:0] rand_a = $urandom();
            logic [31:0] rand_b = $urandom();
            logic [31:0] rand_sum = rand_a + rand_b;
            
            a = rand_a;
            b = rand_b;
            #10;
            
            if (c !== rand_sum) begin
                $display("  FAIL[%0d]: %h + %h = %h (Expected %h)", 
                         i, a, b, c, rand_sum);
                error_count++;
            end
            else begin
                $display("  PASS[%0d]: %h + %h = %h", i, a, b, c);
            end
        end
        
        // Test Case 5: Timing checks
        $display("\n[TEST 5] Timing checks");
        a = 32'h12345678;
        b = 32'h9ABCDEF0;
        #1; // Check propagation delay
        if (c === 32'bx) $display("  PASS: Output not ready at 1ns");
        else $display("  WARNING: Output ready too fast at 1ns");
        
        #(CLK_PERIOD - 1);
        if (c === (32'h12345678 + 32'h9ABCDEF0)) 
            $display("  PASS: Output stable before clock period");
        else
            $display("  FAIL: Output incorrect at %t", $time);
        
        // Summary
        $display("\n\nTest Summary:");
        $display("  Passed tests: %0d", (4 + 4 + 4 + NUM_TESTS + 2) - error_count);
        $display("  Failed tests: %0d", error_count);
        $display("\nSimulation %s", (error_count ? "FAILED" : "PASSED"));
        $finish;
    end
    
    // Test task
    task test_addition(input [31:0] a_val, b_val, exp_val, input string test_name);
        a = a_val;
        b = b_val;
        #10;  // Allow time for calculation
        
        if (c === exp_val) begin
            $display("  PASS: %-20s %h + %h = %h", test_name, a, b, c);
        end else begin
            $display("  FAIL: %-20s %h + %h = %h (Expected %h)", test_name, a, b, c, exp_val);
            error_count++;
        end
    endtask
    
    // Waveform dumping
    initial begin
        $dumpfile("tb_pc_adder.vcd");
        $dumpvars(0, tb_pc_adder);
    end
    
endmodule

riscv_pipe_implt/riscv_pipe_implt.sim/sim_1/behav/xsim/tb_pc_adder.vcd
$date
   Tue Jun 24 13:54:49 2025
$end

$version
  2023.2
  $dumpfile ("tb_pc_adder.vcd") 
$end

$timescale
  1ps
$end

$scope module tb_pc_adder $end
$var reg 32 ! a [31:0] $end
$var reg 32 " b [31:0] $end
$var reg 32 # c [31:0] $end
$var reg 32 $ expected_c [31:0] $end
$var reg 32 % error_count [31:0] $end
$var reg 1 & clk $end
$scope module dut $end
$var wire 32 ' a [31:0] $end
$var wire 32 ( b [31:0] $end
$var wire 32 ) c [31:0] $end
$upscope $end
$scope begin Block65_2 $end
$var reg 32 * i [31:0] $end
$scope begin Block65_3 $end
$var reg 32 + rand_a [31:0] $end
$var reg 32 , rand_b [31:0] $end
$var reg 32 - rand_sum [31:0] $end
$upscope $end
$upscope $end
$scope task test_addition $end
$var reg 32 . a_val [31:0] $end
$var reg 32 / b_val [31:0] $end
$var reg 32 0 exp_val [31:0] $end
$upscope $end
$upscope $end
$enddefinitions $end

#0
$dumpvars
b0 !
b0 "
b0 #
bx $
b0 %
0&
b0 '
b0 (
b0 )
b0 *
bx +
bx ,
bx -
b0 .
b0 /
b0 0
$end

#5000
1&

#10000
b1 !
b1 "
b10 #
0&
b1 '
b1 (
b10 )
b1 .
b1 /
b10 0

#15000
1&

#20000
b1010 !
b101 "
b1111 #
0&
b1010 '
b101 (
b1111 )
b1010 .
b101 /
b1111 0

#25000
1&

#30000
b1111111111111111 !
b1 "
b10000000000000000 #
0&
b1111111111111111 '
b1 (
b10000000000000000 )
b1111111111111111 .
b1 /
b10000000000000000 0

#35000
1&

#40000
b1111111111111111111111111111111 !
b10000000000000000000000000000000 #
0&
b1111111111111111111111111111111 '
b10000000000000000000000000000000 )
b1111111111111111111111111111111 .
b10000000000000000000000000000000 0

#45000
1&

#50000
b10000000000000000000000000000000 !
b11111111111111111111111111111111 "
b1111111111111111111111111111111 #
0&
b10000000000000000000000000000000 '
b11111111111111111111111111111111 (
b1111111111111111111111111111111 )
b10000000000000000000000000000000 .
b11111111111111111111111111111111 /
b1111111111111111111111111111111 0

#55000
1&

#60000
b11111111111111111111111111111111 !
b1 "
b0 #
0&
b11111111111111111111111111111111 '
b1 (
b0 )
b11111111111111111111111111111111 .
b1 /
b0 0

#65000
1&

#70000
b11111111111111111111111111111111 "
b11111111111111111111111111111110 #
0&
b11111111111111111111111111111111 (
b11111111111111111111111111111110 )
b11111111111111111111111111111111 /
b11111111111111111111111111111110 0

#75000
1&

#80000
b11111111111111111111111111111110 !
b10 "
b0 #
0&
b11111111111111111111111111111110 '
b10 (
b0 )
b11111111111111111111111111111110 .
b10 /
b0 0

#85000
1&

#90000
b11111111111111111111111111110000 !
b100000 "
b10000 #
0&
b11111111111111111111111111110000 '
b100000 (
b10000 )
b11111111111111111111111111110000 .
b100000 /
b10000 0

#95000
1&

#100000
b10000000000000000000000000000000 !
b1111111111111111111111111111111 "
b11111111111111111111111111111111 #
0&
b10000000000000000000000000000000 '
b1111111111111111111111111111111 (
b11111111111111111111111111111111 )
b10000000000000000000000000000000 .
b1111111111111111111111111111111 /
b11111111111111111111111111111111 0

#105000
1&

#110000
b11000000000000000000000000000000 !
b11000000000000000000000000000000 "
b10000000000000000000000000000000 #
0&
b11000000000000000000000000000000 '
b11000000000000000000000000000000 (
b10000000000000000000000000000000 )
b11000000000000000000000000000000 .
b11000000000000000000000000000000 /
b10000000000000000000000000000000 0

#115000
1&

#120000
b10000100001101011001010111001111 !
b1000100001011001001011011001100 "
b11001000011000100010110010011011 #
0&
b10000100001101011001010111001111 '
b1000100001011001001011011001100 (
b11001000011000100010110010011011 )
b10000100001101011001010111001111 +
b1000100001011001001011011001100 ,
b11001000011000100010110010011011 -

#125000
1&

#130000
b100110001101001000011001010110 !
b110110010101000111110100101100 "
b1011100100010010000001110000010 #
0&
b100110001101001000011001010110 '
b110110010101000111110100101100 (
b1011100100010010000001110000010 )
b1 *
b100110001101001000011001010110 +
b110110010101000111110100101100 ,
b1011100100010010000001110000010 -

#135000
1&

#140000
b1111010100011110001001100110111 !
b111110111111111000000010101111 "
b10111001100011101001001111100110 #
0&
b1111010100011110001001100110111 '
b111110111111111000000010101111 (
b10111001100011101001001111100110 )
b10 *
b1111010100011110001001100110111 +
b111110111111111000000010101111 ,
b10111001100011101001001111100110 -

#145000
1&

#150000
b10100110000110010111101110010001 !
b1111110110001001010100100000110 "
b100100110111100010010010010111 #
0&
b10100110000110010111101110010001 '
b1111110110001001010100100000110 (
b100100110111100010010010010111 )
b11 *
b10100110000110010111101110010001 +
b1111110110001001010100100000110 ,
b100100110111100010010010010111 -

#155000
1&

#160000
b10000011001011000001011101111100 !
b1001100010011100000000111100111 "
b11001111011110100001100101100011 #
0&
b10000011001011000001011101111100 '
b1001100010011100000000111100111 (
b11001111011110100001100101100011 )
b100 *
b10000011001011000001011101111100 +
b1001100010011100000000111100111 ,
b11001111011110100001100101100011 -

#165000
1&

#170000
b110101000110010010011000110010 !
b1111101101110110010101010110011 "
b10110010110101000101000011100101 #
0&
b110101000110010010011000110010 '
b1111101101110110010101010110011 (
b10110010110101000101000011100101 )
b101 *
b110101000110010010011000110010 +
b1111101101110110010101010110011 ,
b10110010110101000101000011100101 -

#175000
1&

#180000
b10001011010011011000001010010111 !
b1011011001100101010000111000011 "
b11100110100000000010010001011010 #
0&
b10001011010011011000001010010111 '
b1011011001100101010000111000011 (
b11100110100000000010010001011010 )
b110 *
b10001011010011011000001010010111 +
b1011011001100101010000111000011 ,
b11100110100000000010010001011010 -

#185000
1&

#190000
b1111100011111111101001110111001 !
b10001110011110011001101000010011 "
b1010111110010110110111001100 #
0&
b1111100011111111101001110111001 '
b10001110011110011001101000010011 (
b1010111110010110110111001100 )
b111 *
b1111100011111111101001110111001 +
b10001110011110011001101000010011 ,
b1010111110010110110111001100 -

#195000
1&

#200000
b10100111100000001010001110101011 !
b110001100110001111100111101011 "
b11011001000110011001110110010110 #
0&
b10100111100000001010001110101011 '
b110001100110001111100111101011 (
b11011001000110011001110110010110 )
b1000 *
b10100111100000001010001110101011 +
b110001100110001111100111101011 ,
b11011001000110011001110110010110 -

#205000
1&

#210000
b10001100001101001100010011000110 !
b10110010110011100010011001000010 "
b111111000000101110101100001000 #
0&
b10001100001101001100010011000110 '
b10110010110011100010011001000010 (
b111111000000101110101100001000 )
b1001 *
b10001100001101001100010011000110 +
b10110010110011100010011001000010 ,
b111111000000101110101100001000 -

#215000
1&

#220000
b10001100110010111001101110101111 !
b10001000101101001001100001111111 "
b10101100000000011010000101110 #
0&
b10001100110010111001101110101111 '
b10001000101101001001100001111111 (
b10101100000000011010000101110 )
b1010 *
b10001100110010111001101110101111 +
b10001000101101001001100001111111 ,
b10101100000000011010000101110 -

#225000
1&

#230000
b1000001010001111100000001010101 !
b10110100010011000011111101011010 "
b11110101100100111111111110101111 #
0&
b1000001010001111100000001010101 '
b10110100010011000011111101011010 (
b11110101100100111111111110101111 )
b1011 *
b1000001010001111100000001010101 +
b10110100010011000011111101011010 ,
b11110101100100111111111110101111 -

#235000
1&

#240000
b111010010011011001001001101010 !
b1001101011111001000010100011011 "
b10000111110010100001011110000101 #
0&
b111010010011011001001001101010 '
b1001101011111001000010100011011 (
b10000111110010100001011110000101 )
b1100 *
b111010010011011001001001101010 +
b1001101011111001000010100011011 ,
b10000111110010100001011110000101 -

#245000
1&

#250000
b1100111000110100110010110011100 !
b1000111000110010010111000011001 "
b10101110001100111001001110110101 #
0&
b1100111000110100110010110011100 '
b1000111000110010010111000011001 (
b10101110001100111001001110110101 )
b1101 *
b1100111000110100110010110011100 +
b1000111000110010010111000011001 ,
b10101110001100111001001110110101 -

#255000
1&

#260000
b1010110001100010001110110011010 !
b10101000011000100010010111110001 "
b11111110100100110100001110001011 #
0&
b1010110001100010001110110011010 '
b10101000011000100010010111110001 (
b11111110100100110100001110001011 )
b1110 *
b1010110001100010001110110011010 +
b10101000011000100010010111110001 ,
b11111110100100110100001110001011 -

#265000
1&

#270000
b1111011011001010110110101110011 !
b10000011111101011000000000100 "
b10001011111001000001110101110111 #
0&
b1111011011001010110110101110011 '
b10000011111101011000000000100 (
b10001011111001000001110101110111 )
b1111 *
b1111011011001010110110101110011 +
b10000011111101011000000000100 ,
b10001011111001000001110101110111 -

#275000
1&

#280000
b1110101110111101010101100001100 !
b1100010011111111101001100001111 "
b11011000010111100111111000011011 #
0&
b1110101110111101010101100001100 '
b1100010011111111101001100001111 (
b11011000010111100111111000011011 )
b10000 *
b1110101110111101010101100001100 +
b1100010011111111101001100001111 ,
b11011000010111100111111000011011 -

#285000
1&

#290000
b1010111100101111101111000011110 !
b1001100000011111100100010100110 "
b10100011101001111010011011000100 #
0&
b1010111100101111101111000011110 '
b1001100000011111100100010100110 (
b10100011101001111010011011000100 )
b10001 *
b1010111100101111101111000011110 +
b1001100000011111100100010100110 ,
b10100011101001111010011011000100 -

#295000
1&

#300000
b1010111000011111100100000000 !
b1010010111111010100101110010001 "
b1011101110111110100010010010001 #
0&
b1010111000011111100100000000 '
b1010010111111010100101110010001 (
b1011101110111110100010010010001 )
b10010 *
b1010111000011111100100000000 +
b1010010111111010100101110010001 ,
b1011101110111110100010010010001 -

#305000
1&

#310000
b1011100100011100111100010101010 !
b110000001010010000001100 "
b1011101010011110001110010110110 #
0&
b1011100100011100111100010101010 '
b110000001010010000001100 (
b1011101010011110001110010110110 )
b10011 *
b1011100100011100111100010101010 +
b110000001010010000001100 ,
b1011101010011110001110010110110 -

#315000
1&

#320000
b10110101011111010001111010100001 !
b110100001001100101011011001000 "
b11101001101000110111010101101001 #
0&
b10110101011111010001111010100001 '
b110100001001100101011011001000 (
b11101001101000110111010101101001 )
b10100 *
b10110101011111010001111010100001 +
b110100001001100101011011001000 ,
b11101001101000110111010101101001 -

#325000
1&

#330000
b1001100110100000110110010110010 !
b1000000010111110001011110100001 "
b10001101001011111000010001010011 #
0&
b1001100110100000110110010110010 '
b1000000010111110001011110100001 (
b10001101001011111000010001010011 )
b10101 *
b1001100110100000110110010110010 +
b1000000010111110001011110100001 ,
b10001101001011111000010001010011 -

#335000
1&

#340000
b10000111001000111010001001011010 !
b10101001010111101110010101011101 "
b110000100000101000011110110111 #
0&
b10000111001000111010001001011010 '
b10101001010111101110010101011101 (
b110000100000101000011110110111 )
b10110 *
b10000111001000111010001001011010 +
b10101001010111101110010101011101 ,
b110000100000101000011110110111 -

#345000
1&

#350000
b1000001000111111011101110101110 !
b10111100101000001100000011111011 "
b11111101110000000111110010101001 #
0&
b1000001000111111011101110101110 '
b10111100101000001100000011111011 (
b11111101110000000111110010101001 )
b10111 *
b1000001000111111011101110101110 +
b10111100101000001100000011111011 ,
b11111101110000000111110010101001 -

#355000
1&

#360000
b1011101100001010011110000100101 !
b1101111100000010100001100000 "
b1101011011101010110010010000101 #
0&
b1011101100001010011110000100101 '
b1101111100000010100001100000 (
b1101011011101010110010010000101 )
b11000 *
b1011101100001010011110000100101 +
b1101111100000010100001100000 ,
b1101011011101010110010010000101 -

#365000
1&

#370000
b1111100111111111101100010011100 !
b1100100101010001101111001111111 "
b11100001101010001011011100011011 #
0&
b1111100111111111101100010011100 '
b1100100101010001101111001111111 (
b11100001101010001011011100011011 )
b11001 *
b1111100111111111101100010011100 +
b1100100101010001101111001111111 ,
b11100001101010001011011100011011 -

#375000
1&

#380000
b110111010011110000110110111101 !
b111110000111111001010001001010 "
b1110101011011101010001000000111 #
0&
b110111010011110000110110111101 '
b111110000111111001010001001010 (
b1110101011011101010001000000111 )
b11010 *
b110111010011110000110110111101 +
b111110000111111001010001001010 ,
b1110101011011101010001000000111 -

#385000
1&

#390000
b100001010010011001111101111010 !
b10010100110101000100100111100011 "
b10110110000111011110100101011101 #
0&
b100001010010011001111101111010 '
b10010100110101000100100111100011 (
b10110110000111011110100101011101 )
b11011 *
b100001010010011001111101111010 +
b10010100110101000100100111100011 ,
b10110110000111011110100101011101 -

#395000
1&

#400000
b1001100000011111011110010101011 !
b10011110010010010111100000010111 "
b11101010010110010011010011000010 #
0&
b1001100000011111011110010101011 '
b10011110010010010111100000010111 (
b11101010010110010011010011000010 )
b11100 *
b1001100000011111011110010101011 +
b10011110010010010111100000010111 ,
b11101010010110010011010011000010 -

#405000
1&

#410000
b1111001011111010010100001100010 !
b11010111101100101001101000 "
b1111100110110111111001011001010 #
0&
b1111001011111010010100001100010 '
b11010111101100101001101000 (
b1111100110110111111001011001010 )
b11101 *
b1111001011111010010100001100010 +
b11010111101100101001101000 ,
b1111100110110111111001011001010 -

#415000
1&

#420000
b1011100011010010000110001100001 !
b10011010110001101100011111011101 "
b11110111001011111101010000111110 #
0&
b1011100011010010000110001100001 '
b10011010110001101100011111011101 (
b11110111001011111101010000111110 )
b11110 *
b1011100011010010000110001100001 +
b10011010110001101100011111011101 ,
b11110111001011111101010000111110 -

#425000
1&

#430000
b11000001100110001010001001011 !
b101000011110001100100100001100 "
b1000000101010111101110101010111 #
0&
b11000001100110001010001001011 '
b101000011110001100100100001100 (
b1000000101010111101110101010111 )
b11111 *
b11000001100110001010001001011 +
b101000011110001100100100001100 ,
b1000000101010111101110101010111 -

#435000
1&

#440000
b10111001000100000011111111110100 !
b10010001101100000011110010101110 "
b1001010110000000111110010100010 #
0&
b10111001000100000011111111110100 '
b10010001101100000011110010101110 (
b1001010110000000111110010100010 )
b100000 *
b10111001000100000011111111110100 +
b10010001101100000011110010101110 ,
b1001010110000000111110010100010 -

#445000
1&

#450000
b10101011110101111001001101110101 !
b10101011110010100110001010101 "
b11000001010100001101111111001010 #
0&
b10101011110101111001001101110101 '
b10101011110010100110001010101 (
b11000001010100001101111111001010 )
b100001 *
b10101011110101111001001101110101 +
b10101011110010100110001010101 ,
b11000001010100001101111111001010 -

#455000
1&

#460000
b10101100011101110000010010001011 !
b1000100000010101010011111000000 "
b11110000100000011010110001001011 #
0&
b10101100011101110000010010001011 '
b1000100000010101010011111000000 (
b11110000100000011010110001001011 )
b100010 *
b10101100011101110000010010001011 +
b1000100000010101010011111000000 ,
b11110000100000011010110001001011 -

#465000
1&

#470000
b10111101111100100001010101100010 !
b1100101100001110100010001111111 "
b100011011110010101100111100001 #
0&
b10111101111100100001010101100010 '
b1100101100001110100010001111111 (
b100011011110010101100111100001 )
b100011 *
b10111101111100100001010101100010 +
b1100101100001110100010001111111 ,
b100011011110010101100111100001 -

#475000
1&

#480000
b1010101101110101110010001101110 !
b1101001110010011010100011010111 "
b10111111100001001000110101000101 #
0&
b1010101101110101110010001101110 '
b1101001110010011010100011010111 (
b10111111100001001000110101000101 )
b100100 *
b1010101101110101110010001101110 +
b1101001110010011010100011010111 ,
b10111111100001001000110101000101 -

#485000
1&

#490000
b1111011000000001001000011010100 !
b10001100011110100011111001 "
b1111101001100100111100111001101 #
0&
b1111011000000001001000011010100 '
b10001100011110100011111001 (
b1111101001100100111100111001101 )
b100101 *
b1111011000000001001000011010100 +
b10001100011110100011111001 ,
b1111101001100100111100111001101 -

#495000
1&

#500000
b101101110101000101000010010111 !
b111000111100101010011000110110 "
b1100110110001101111011011001101 #
0&
b101101110101000101000010010111 '
b111000111100101010011000110110 (
b1100110110001101111011011001101 )
b100110 *
b101101110101000101000010010111 +
b111000111100101010011000110110 ,
b1100110110001101111011011001101 -

#505000
1&

#510000
b1100111101110010010110101111000 !
b10000011100011110011010100000110 "
b11101011010010000110001001111110 #
0&
b1100111101110010010110101111000 '
b10000011100011110011010100000110 (
b11101011010010000110001001111110 )
b100111 *
b1100111101110010010110101111000 +
b10000011100011110011010100000110 ,
b11101011010010000110001001111110 -

#515000
1&

#520000
b100010101111000100111100001101 !
b1100010101110011011111001001101 "
b10000101011101100000110101011010 #
0&
b100010101111000100111100001101 '
b1100010101110011011111001001101 (
b10000101011101100000110101011010 )
b101000 *
b100010101111000100111100001101 +
b1100010101110011011111001001101 ,
b10000101011101100000110101011010 -

#525000
1&

#530000
b101110000010001110111111111 !
b1010000100100001001111110100101 "
b1010110010100011011110110100100 #
0&
b101110000010001110111111111 '
b1010000100100001001111110100101 (
b1010110010100011011110110100100 )
b101001 *
b101110000010001110111111111 +
b1010000100100001001111110100101 ,
b1010110010100011011110110100100 -

#535000
1&

#540000
b11011101011000110010010000011 !
b1101101011110100100101101111000 "
b10001001001001101010111111111011 #
0&
b11011101011000110010010000011 '
b1101101011110100100101101111000 (
b10001001001001101010111111111011 )
b101010 *
b11011101011000110010010000011 +
b1101101011110100100101101111000 ,
b10001001001001101010111111111011 -

#545000
1&

#550000
b1010100000111111101010010101011 !
b10111110011010001011001110010001 "
b10010100010001000100000111100 #
0&
b1010100000111111101010010101011 '
b10111110011010001011001110010001 (
b10010100010001000100000111100 )
b101011 *
b1010100000111111101010010101011 +
b10111110011010001011001110010001 ,
b10010100010001000100000111100 -

#555000
1&

#560000
b1010000001101000000100111000101 !
b1011001111000001111001010101010 "
b10101010000101001111110001101111 #
0&
b1010000001101000000100111000101 '
b1011001111000001111001010101010 (
b10101010000101001111110001101111 )
b101100 *
b1010000001101000000100111000101 +
b1011001111000001111001010101010 ,
b10101010000101001111110001101111 -

#565000
1&

#570000
b10001110111110010101001100110110 !
b1101011111000000110111001001000 "
b11111010110110011100000101111110 #
0&
b10001110111110010101001100110110 '
b1101011111000000110111001001000 (
b11111010110110011100000101111110 )
b101101 *
b10001110111110010101001100110110 +
b1101011111000000110111001001000 ,
b11111010110110011100000101111110 -

#575000
1&

#580000
b1000111010110110011111000100010 !
b1100011000110010010011111100001 "
b10101010011101000110011000000011 #
0&
b1000111010110110011111000100010 '
b1100011000110010010011111100001 (
b10101010011101000110011000000011 )
b101110 *
b1000111010110110011111000100010 +
b1100011000110010010011111100001 ,
b10101010011101000110011000000011 -

#585000
1&

#590000
b101010010010010010000111011001 !
b10111100011110100011111100111 "
b1000001110110000110100111000000 #
0&
b101010010010010010000111011001 '
b10111100011110100011111100111 (
b1000001110110000110100111000000 )
b101111 *
b101010010010010010000111011001 +
b10111100011110100011111100111 ,
b1000001110110000110100111000000 -

#595000
1&

#600000
b111100111110100001101010001011 !
b111001010000100111010100001111 "
b1110110001111001000111110011010 #
0&
b111100111110100001101010001011 '
b111001010000100111010100001111 (
b1110110001111001000111110011010 )
b110000 *
b111100111110100001101010001011 +
b111001010000100111010100001111 ,
b1110110001111001000111110011010 -

#605000
1&

#610000
b10000011011011111011011000110000 !
b10000100010101010101100010101110 "
b111110001010000111011011110 #
0&
b10000011011011111011011000110000 '
b10000100010101010101100010101110 (
b111110001010000111011011110 )
b110001 *
b10000011011011111011011000110000 +
b10000100010101010101100010101110 ,
b111110001010000111011011110 -

#615000
1&

#620000
b11100010110111001110011110000 !
b101101101110001101100000001001 "
b1001010000101000111010011111001 #
0&
b11100010110111001110011110000 '
b101101101110001101100000001001 (
b1001010000101000111010011111001 )
b110010 *
b11100010110111001110011110000 +
b101101101110001101100000001001 ,
b1001010000101000111010011111001 -

#625000
1&

#630000
b11011111001001010000010010101 !
b1011001010101011011011101111100 "
b1110101001110100101100000010001 #
0&
b11011111001001010000010010101 '
b1011001010101011011011101111100 (
b1110101001110100101100000010001 )
b110011 *
b11011111001001010000010010101 +
b1011001010101011011011101111100 ,
b1110101001110100101100000010001 -

#635000
1&

#640000
b1100110111110110100110100011001 !
b11111010101000101011011000101 "
b10000110010011111010001111011110 #
0&
b1100110111110110100110100011001 '
b11111010101000101011011000101 (
b10000110010011111010001111011110 )
b110100 *
b1100110111110110100110100011001 +
b11111010101000101011011000101 ,
b10000110010011111010001111011110 -

#645000
1&

#650000
b1011101101010110001000000101010 !
b11010101101110101000001001 "
b1100001000000011111101000110011 #
0&
b1011101101010110001000000101010 '
b11010101101110101000001001 (
b1100001000000011111101000110011 )
b110101 *
b1011101101010110001000000101010 +
b11010101101110101000001001 ,
b1100001000000011111101000110011 -

#655000
1&

#660000
b1001101000011010010111011001111 !
b1111001100011111011000010111111 "
b11000110100111001101111110001110 #
0&
b1001101000011010010111011001111 '
b1111001100011111011000010111111 (
b11000110100111001101111110001110 )
b110110 *
b1001101000011010010111011001111 +
b1111001100011111011000010111111 ,
b11000110100111001101111110001110 -

#665000
1&

#670000
b1011100101011001010000110000101 !
b10110100000010000111101111101000 "
b10000101101010001110101101101 #
0&
b1011100101011001010000110000101 '
b10110100000010000111101111101000 (
b10000101101010001110101101101 )
b110111 *
b1011100101011001010000110000101 +
b10110100000010000111101111101000 ,
b10000101101010001110101101101 -

#675000
1&

#680000
b10011000111001000000011110000101 !
b111010010101111011000110101111 "
b11010011001110111011100100110100 #
0&
b10011000111001000000011110000101 '
b111010010101111011000110101111 (
b11010011001110111011100100110100 )
b111000 *
b10011000111001000000011110000101 +
b111010010101111011000110101111 ,
b11010011001110111011100100110100 -

#685000
1&

#690000
b110111010111110110010111110001 !
b1100101111100010011011001010100 "
b10011101010100001001110001000101 #
0&
b110111010111110110010111110001 '
b1100101111100010011011001010100 (
b10011101010100001001110001000101 )
b111001 *
b110111010111110110010111110001 +
b1100101111100010011011001010100 ,
b10011101010100001001110001000101 -

#695000
1&

#700000
b10110011111001110110001001101111 !
b10010100000011000000011101110111 "
b1000111111100110110100111100110 #
0&
b10110011111001110110001001101111 '
b10010100000011000000011101110111 (
b1000111111100110110100111100110 )
b111010 *
b10110011111001110110001001101111 +
b10010100000011000000011101110111 ,
b1000111111100110110100111100110 -

#705000
1&

#710000
b10011001111110011011001000111100 !
b1001100110010110110100111110100 "
b11100110110001010001110000110000 #
0&
b10011001111110011011001000111100 '
b1001100110010110110100111110100 (
b11100110110001010001110000110000 )
b111011 *
b10011001111110011011001000111100 +
b1001100110010110110100111110100 ,
b11100110110001010001110000110000 -

#715000
1&

#720000
b1001110011000111011100100100110 !
b1010001010110010001100000101101 "
b10011111101111001101000101010011 #
0&
b1001110011000111011100100100110 '
b1010001010110010001100000101101 (
b10011111101111001101000101010011 )
b111100 *
b1001110011000111011100100100110 +
b1010001010110010001100000101101 ,
b10011111101111001101000101010011 -

#725000
1&

#730000
b10110010101111001010000001001000 !
b10010010110001101110010101 "
b10110101000001111011101111011101 #
0&
b10110010101111001010000001001000 '
b10010010110001101110010101 (
b10110101000001111011101111011101 )
b111101 *
b10110010101111001010000001001000 +
b10010010110001101110010101 ,
b10110101000001111011101111011101 -

#735000
1&

#740000
b1100101011001010001111110100100 !
b1001100101101100101001010000100 "
b10110010000110110111001000101000 #
0&
b1100101011001010001111110100100 '
b1001100101101100101001010000100 (
b10110010000110110111001000101000 )
b111110 *
b1100101011001010001111110100100 +
b1001100101101100101001010000100 ,
b10110010000110110111001000101000 -

#745000
1&

#750000
b1001111000101101000010110001001 !
b10110011110010001101100011001011 "
b10110111110101111001010100 #
0&
b1001111000101101000010110001001 '
b10110011110010001101100011001011 (
b10110111110101111001010100 )
b111111 *
b1001111000101101000010110001001 +
b10110011110010001101100011001011 ,
b10110111110101111001010100 -

#755000
1&

#760000
b11110000011110110101010110001 !
b1110100110010010111010001 "
b11111111000101001000010000010 #
0&
b11110000011110110101010110001 '
b1110100110010010111010001 (
b11111111000101001000010000010 )
b1000000 *
b11110000011110110101010110001 +
b1110100110010010111010001 ,
b11111111000101001000010000010 -

#765000
1&

#770000
b110110000100111111010001100000 !
b10000011011101001000101001010110 "
b10111001100010000111111010110110 #
0&
b110110000100111111010001100000 '
b10000011011101001000101001010110 (
b10111001100010000111111010110110 )
b1000001 *
b110110000100111111010001100000 +
b10000011011101001000101001010110 ,
b10111001100010000111111010110110 -

#775000
1&

#780000
b1001110100010010111100001010101 !
b10000101001010100111100111101010 "
b11010011101100111111001000111111 #
0&
b1001110100010010111100001010101 '
b10000101001010100111100111101010 (
b11010011101100111111001000111111 )
b1000010 *
b1001110100010010111100001010101 +
b10000101001010100111100111101010 ,
b11010011101100111111001000111111 -

#785000
1&

#790000
b10110111001111010110001100100001 !
b1101100100110001110001100000111 "
b100011110101100100011000101000 #
0&
b10110111001111010110001100100001 '
b1101100100110001110001100000111 (
b100011110101100100011000101000 )
b1000011 *
b10110111001111010110001100100001 +
b1101100100110001110001100000111 ,
b100011110101100100011000101000 -

#795000
1&

#800000
b110111111011001111110111011 !
b1101101010100010101011110000001 "
b1110100010011101111011100111100 #
0&
b110111111011001111110111011 '
b1101101010100010101011110000001 (
b1110100010011101111011100111100 )
b1000100 *
b110111111011001111110111011 +
b1101101010100010101011110000001 ,
b1110100010011101111011100111100 -

#805000
1&

#810000
b1110000000011010110110101011101 !
b1010101100001110001100000010001 "
b11000101100101001000010101101110 #
0&
b1110000000011010110110101011101 '
b1010101100001110001100000010001 (
b11000101100101001000010101101110 )
b1000101 *
b1110000000011010110110101011101 +
b1010101100001110001100000010001 ,
b11000101100101001000010101101110 -

#815000
1&

#820000
b1110010011110111101000101101011 !
b10100111010010101101000001111110 "
b11001110001101010000111101001 #
0&
b1110010011110111101000101101011 '
b10100111010010101101000001111110 (
b11001110001101010000111101001 )
b1000110 *
b1110010011110111101000101101011 +
b10100111010010101101000001111110 ,
b11001110001101010000111101001 -

#825000
1&

