src/pc_module.v
module pc_module (
    input  wire        clk,      // System clock
    input  wire        rst,      // Active-low synchronous reset
    input  wire [31:0] pc_next,  // Next PC value
    output reg  [31:0] pc        // Current PC value
);

    // Program Counter register
    always @(posedge clk) begin
        if (rst)  pc <= 32'h0;   // Synchronous reset
        else      pc <= pc_next; // Normal operation
    end

endmodule

riscv_pipe_implt/riscv_pipe_implt.srcs/sim_1/new/tb_pc_module.sv
`timescale 1ns / 1ps

module tb_pc_module();
    // Clock parameters
    parameter CLK_PERIOD = 10;  // 100 MHz clock

    // DUT signals
    logic        clk;       // System clock
    logic        rst;       // Active-low synchronous reset
    logic [31:0] pc_next;   // Next PC value
    logic [31:0] pc;        // Current PC value
    
    // Instantiate DUT
    pc_module dut (
        .clk(clk),
        .rst(rst),
        .pc_next(pc_next),
        .pc(pc)
    );
    
    // Clock generation
    initial begin
        clk = 1'b0;
        forever #(CLK_PERIOD/2) clk = ~clk;
    end
    
    // Reset generation
    task apply_reset();
        rst = 1'b0;   // Assert reset
        @(posedge clk);
        #1;           // Offset from clock edge
        rst = 1'b1;   // Deassert reset
        @(posedge clk);
    endtask
    
    // Main test sequence
    initial begin
        // Initialize inputs
        rst = 1'b1;
        pc_next = '0;
        
        // Open simulation results file
        $timeformat(-9, 2, " ns", 10);
        $display("\nStarting PC Module Testbench\n");
        
        // Test Case 1: Power-on reset
        $display("[TEST 1] Power-on reset");
        apply_reset();
        #1;  // Wait for output update
        assert (pc === 32'h0) 
            else $error("Reset failed! PC = %0h", pc);
        $display("  PASS: Reset to 0x0 verified\n");
        
        // Test Case 2: Basic operation
        $display("[TEST 2] Basic operation");
        pc_next = 32'h0000_1000;
        @(posedge clk);
        #1;  // Wait for output update
        assert (pc === pc_next)
            else $error("PC update failed! Expected %0h, Got %0h", pc_next, pc);
        $display("  PASS: PC updated to 0x%0h\n", pc);
        
        // Test Case 3: Sequential updates
        $display("[TEST 3] Sequential updates");
        for (int i = 1; i <= 5; i++) begin
            pc_next = pc + 4;
            @(posedge clk);
            #1;  // Wait for output update
            assert (pc === pc_next)
                else $error("Update %0d failed! Expected %0h, Got %0h", i, pc_next, pc);
            $display("  PASS[%0d]: PC = 0x%0h", i, pc);
        end
        $display("");
        
        // Test Case 4: Reset during operation
        $display("[TEST 4] Reset during operation");
        pc_next = 32'hDEAD_BEEF;
        @(posedge clk);
        apply_reset();
        #1;  // Wait for output update
        assert (pc === 32'h0)
            else $error("Reset during operation failed! PC = %0h", pc);
        $display("  PASS: Reset during operation verified\n");
        
        // Test Case 5: Boundary values
        $display("[TEST 5] Boundary values");
        test_boundary(32'h0000_0000);
        test_boundary(32'hFFFF_FFFF);
        test_boundary(32'h8000_0000);
        test_boundary(32'h7FFF_FFFF);
        $display("");
        
        // Test Case 6: Random stimulus
        $display("[TEST 6] Random stimulus (10 cycles)");
        for (int i = 0; i < 10; i++) begin
            pc_next = $urandom();
            @(posedge clk);
            #1;  // Wait for output update
            assert (pc === pc_next)
                else $error("Random test %0d failed! Expected %0h, Got %0h", i, pc_next, pc);
            $display("  RAND[%0d]: PC = 0x%0h", i, pc);
        end
        $display("");
        
        // End simulation
        $display("\nAll tests passed successfully!");
        $finish;
    end
    
    // Task to test boundary values
    task test_boundary(input [31:0] value);
        pc_next = value;
        @(posedge clk);
        #1;  // Wait for output update
        assert (pc === value)
            else $error("Boundary test failed for 0x%0h! Got 0x%0h", value, pc);
        $display("  PASS: PC = 0x%0h", value);
    endtask
    
    // Coverage collection
    covergroup pc_cg @(posedge clk);
        reset_state: coverpoint rst {
            bins active_low = {0};
            bins inactive   = {1};
        }
        pc_value: coverpoint pc {
            bins zero    = {0};
            bins max     = {32'hFFFF_FFFF};
            bins min     = {32'h0000_0001};
            bins aligned = {[0:$]} with (item % 4 == 0);
            bins unaligned = {[0:$]} with (item % 4 != 0);
        }
        pc_transition: coverpoint pc {
            bins inc4 = (0 => 4);
        }
        reset_during_op: cross reset_state, pc_value {
            ignore_bins normal = binsof(reset_state) intersect {1};
        }
    endgroup
    
    initial begin
        pc_cg cg_inst = new();
    end
    
    // Waveform dumping
    initial begin
        $dumpfile("tb_pc_module.vcd");
        $dumpvars(0, tb_pc_module);
    end
endmodule

riscv_pipe_implt/riscv_pipe_implt.sim/sim_1/behav/xsim/tb_pc_module.vcd
$date
   Tue Jun 24 13:10:40 2025
$end

$version
  2023.2
  $dumpfile ("tb_pc_module.vcd") 
$end

$timescale
  1ps
$end

$scope module tb_pc_module $end
$var reg 1 ! clk $end
$var reg 1 " rst $end
$var reg 32 # pc_next [31:0] $end
$var reg 32 $ pc [31:0] $end
$scope module dut $end
$var wire 1 % clk $end
$var wire 1 & rst $end
$var wire 32 ' pc_next [31:0] $end
$var reg 32 $ pc [31:0] $end
$upscope $end
$scope begin Block65_3 $end
$var reg 32 ( i [31:0] $end
$upscope $end
$scope begin Block95_4 $end
$var reg 32 ) i [31:0] $end
$upscope $end
$scope task apply_reset $end
$upscope $end
$scope task test_boundary $end
$var reg 32 * value [31:0] $end
$upscope $end
$scope function xlnx_isim_covergroup_pc_cg::new $end
$upscope $end
$scope function xlnx_isim_covergroup_pc_cg::update $end
$upscope $end
$scope function xlnx_isim_covergroup_pc_cg::xlnx_isim_covergroup_sample $end
$upscope $end
$upscope $end
$enddefinitions $end

#0
$dumpvars
0!
0"
b0 #
bx $
0%
0&
b0 '
b0 (
b0 )
bx *
$end

#5000
1!
b0 $
1%

#6000
1"
1&

#10000
0!
0%

#15000
1!
1%

#16000
b1000000000000 #
b1000000000000 '

#20000
0!
0%

#25000
1!
b1000000000000 $
1%

#26000
b1000000000100 #
b1000000000100 '
b1 (

#30000
0!
0%

#35000
1!
b1000000000100 $
1%

#36000
b1000000001000 #
b1000000001000 '
b10 (

#40000
0!
0%

#45000
1!
b1000000001000 $
1%

#46000
b1000000001100 #
b1000000001100 '
b11 (

#50000
0!
0%

#55000
1!
b1000000001100 $
1%

#56000
b1000000010000 #
b1000000010000 '
b100 (

#60000
0!
0%

#65000
1!
b1000000010000 $
1%

#66000
b1000000010100 #
b1000000010100 '
b101 (

#70000
0!
0%

#75000
1!
b1000000010100 $
1%

#76000
b11011110101011011011111011101111 #
b11011110101011011011111011101111 '
b110 (

#80000
0!
0%

#85000
1!
0"
b0 $
1%
0&

#90000
0!
0%

#95000
1!
1%

#96000
1"
1&

#100000
0!
0%

#105000
1!
b11011110101011011011111011101111 $
1%

#106000
b0 #
b0 '
b0 *

#110000
0!
0%

#115000
1!
b0 $
1%

#116000
b11111111111111111111111111111111 #
b11111111111111111111111111111111 '
b11111111111111111111111111111111 *

#120000
0!
0%

#125000
1!
b11111111111111111111111111111111 $
1%

#126000
b10000000000000000000000000000000 #
b10000000000000000000000000000000 '
b10000000000000000000000000000000 *

#130000
0!
0%

#135000
1!
b10000000000000000000000000000000 $
1%

#136000
b1111111111111111111111111111111 #
b1111111111111111111111111111111 '
b1111111111111111111111111111111 *

#140000
0!
0%

#145000
1!
b1111111111111111111111111111111 $
1%

#146000
b1100100110010010011000111011011 #
b1100100110010010011000111011011 '

#150000
0!
0%

#155000
1!
b1100100110010010011000111011011 $
1%

#156000
b1101111101000010010010010111100 #
b1101111101000010010010010111100 '
b1 )

#160000
0!
0%

#165000
1!
b1101111101000010010010010111100 $
1%

#166000
b1010101001111101111000011111100 #
b1010101001111101111000011111100 '
b10 )

#170000
0!
0%

#175000
1!
b1010101001111101111000011111100 $
1%

#176000
b1000110100011001100101010001110 #
b1000110100011001100101010001110 '
b11 )

#180000
0!
0%

#185000
1!
b1000110100011001100101010001110 $
1%

#186000
b1101011001111001111010011110000 #
b1101011001111001111010011110000 '
b100 )

#190000
0!
0%

#195000
1!
b1101011001111001111010011110000 $
1%

#196000
b1011001000000011001111011011101 #
b1011001000000011001111011011101 '
b101 )

#200000
0!
0%

#205000
1!
b1011001000000011001111011011101 $
1%

#206000
b10110100110111111111100011110 #
b10110100110111111111100011110 '
b110 )

#210000
0!
0%

#215000
1!
b10110100110111111111100011110 $
1%

#216000
b1010000000001100010011011001011 #
b1010000000001100010011011001011 '
b111 )

#220000
0!
0%

#225000
1!
b1010000000001100010011011001011 $
1%

#226000
b1001000101000101100001110011001 #
b1001000101000101100001110011001 '
b1000 )

#230000
0!
0%

#235000
1!
b1001000101000101100001110011001 $
1%

#236000
b1101011110110101111000000011011 #
b1101011110110101111000000011011 '
b1001 )

#240000
0!
0%

#245000
1!
b1101011110110101111000000011011 $
1%

#246000
b1010 )
